
README.rst
setup.py
setuptools_pyflakes/__init__.py
setuptools_pyflakes/_version.py
setuptools_pyflakes/setuptools_command.py
setuptools_pyflakes.egg-info/PKG-INFO
setuptools_pyflakes.egg-info/SOURCES.txt
setuptools_pyflakes.egg-info/dependency_links.txt
setuptools_pyflakes.egg-info/entry_points.txt
setuptools_pyflakes.egg-info/not-zip-safe
setuptools_pyflakes.egg-info/requires.txt
setuptools_pyflakes.egg-info/top_level.txt